{
	"name": "dataflow8",
	"properties": {
		"type": "MappingDataFlow",
		"typeProperties": {
			"sources": [
				{
					"dataset": {
						"referenceName": "goods_json",
						"type": "DatasetReference"
					},
					"name": "source1"
				}
			],
			"sinks": [
				{
					"dataset": {
						"referenceName": "goods2_json",
						"type": "DatasetReference"
					},
					"name": "sink1"
				},
				{
					"dataset": {
						"referenceName": "goods2_csv",
						"type": "DatasetReference"
					},
					"name": "sink2"
				}
			],
			"transformations": [
				{
					"name": "Flatten1"
				},
				{
					"name": "Select1"
				}
			],
			"script": "source(output(\n\t\tname as string,\n\t\tlocation as string,\n\t\tsatellites as string[],\n\t\tgoods as (trade as boolean, customers as string[], orders as (orderId as string, orderTotal as double, shipped as (orderItems as (itemName as string, itemQty as string)[]))[])\n\t),\n\tallowSchemaDrift: false,\n\tvalidateSchema: false,\n\tignoreNoFilesFound: false,\n\tdocumentForm: 'arrayOfDocuments') ~> source1\nsource1 foldDown(unroll(goods.orders.shipped.orderItems),\n\tmapColumn(\n\t\tname,\n\t\torderid = goods.orders.orderId,\n\t\tsatellites,\n\t\titemname = goods.orders.shipped.orderItems.itemName,\n\t\titemQty = goods.orders.shipped.orderItems.itemQty\n\t),\n\tpartitionBy('hash', 1),\n\tskipDuplicateMapInputs: false,\n\tskipDuplicateMapOutputs: false) ~> Flatten1\nFlatten1 select(mapColumn(\n\t\tname,\n\t\torderid,\n\t\tsatellites,\n\t\titemname,\n\t\titemQty\n\t),\n\tskipDuplicateMapInputs: true,\n\tskipDuplicateMapOutputs: true) ~> Select1\nSelect1 sink(allowSchemaDrift: true,\n\tvalidateSchema: false,\n\tumask: 0022,\n\tskipDuplicateMapInputs: true,\n\tskipDuplicateMapOutputs: true) ~> sink1\nSelect1 sink(allowSchemaDrift: true,\n\tvalidateSchema: false,\n\tumask: 0022,\n\tskipDuplicateMapInputs: true,\n\tskipDuplicateMapOutputs: true) ~> sink2"
		}
	}
}